<?xml version="1.0" encoding="UTF-8"?>
<!--<plugin>
<type>ClothoFormat</type>
<version>1.0</version>
<classname>org-clothocad-format-bglbricks-connect</classname>
<description>The BglBricks or BBb format:  BamHI/BglII Biobricks</description>
<help>http://andersonlab.qb3.berkeley.edu/Clotho/help1.0.1/help_v1.0.1.html</help>
<displayname>BglBricks</displayname>
<uuid>org-clothocad-format-bglbricks-connect</uuid>
<downloadlink>http://wiki.bu.edu/ece-clotho/index.php/Format:_BglBricks</downloadlink>
<author>J. Christopher Anderson</author>
<iconpath>org/clothocad/format/bglbricks/logo.png</iconpath>
</plugin>-->
<plugin>
    <type>ClothoFormat</type>
    <version>1.0</version>
    <classname>org-clothocad-format-bglbricks-connect</classname>
    <description>The BglBricks or BBb format:  BamHI/BglII Biobricks</description>
    <displayname>BglBricks</displayname>
    <uuid>org-clothocad-format-bglbricks-connect</uuid>
    <!--<screenshotpath></screenshotpath>-->
    <author>J.Christopher Anderson</author>
    <iconpath>org/clothocad/format/bglbricks/logo.png</iconpath>
    <downloadlink>http://wiki.bu.edu/ece-clotho/index.php/Format:_BglBricks</downloadlink>
    <!--<dependency>none</dependency>-->
    <!--<dependency>none2</dependency>-->
    <help>
        <helpurl>http://wiki.bu.edu/ece-clotho/index.php/Format:_BglBricks</helpurl>
        <helpdescription>For more information please see the help url</helpdescription>
        <!--<helpcommand>Command1</helpcommand>-->
        <!--<helpcommand>Command2</helpcommand>-->
    </help>
</plugin>